thsolver/__init__.py
thsolver/config.py
thsolver/dataset.py
thsolver/lr_scheduler.py
thsolver/registry.py
thsolver/sampler.py
thsolver/solver.py
thsolver/tracker.py
thsolver-1.2.0.dist-info/licenses/LICENSE
thsolver-1.2.0.dist-info/METADATA
thsolver-1.2.0.dist-info/WHEEL
thsolver-1.2.0.dist-info/top_level.txt
thsolver-1.2.0.dist-info/RECORD
