Metadata-Version: 2.4
Name: thsolver
Version: 1.2.0
Summary: Solver for PyTorch
Home-page: https://github.com/octree-nn/solver-pytorch
Author: Peng-Shuai Wang
Author-email: wangps@hotmail.com
License: MIT
Classifier: Programming Language :: Python :: 3
Classifier: License :: OSI Approved :: MIT License
Classifier: Operating System :: OS Independent
Requires-Python: >=3.6
License-File: LICENSE
Requires-Dist: torch
Requires-Dist: numpy
Requires-Dist: yacs
Requires-Dist: tqdm
Requires-Dist: packaging
Dynamic: author
Dynamic: author-email
Dynamic: classifier
Dynamic: description
Dynamic: description-content-type
Dynamic: home-page
Dynamic: license
Dynamic: license-file
Dynamic: requires-dist
Dynamic: requires-python
Dynamic: summary
